odoo/addons/sale_partner_selectable_option/README.rst
odoo/addons/sale_partner_selectable_option/__init__.py
odoo/addons/sale_partner_selectable_option/__manifest__.py
odoo/addons/sale_partner_selectable_option/i18n/es.po
odoo/addons/sale_partner_selectable_option/i18n/sale_partner_selectable_option.pot
odoo/addons/sale_partner_selectable_option/migrations/13.0.2.0.0/pre-migration.py
odoo/addons/sale_partner_selectable_option/models/__init__.py
odoo/addons/sale_partner_selectable_option/models/res_partner.py
odoo/addons/sale_partner_selectable_option/models/sale_order.py
odoo/addons/sale_partner_selectable_option/readme/CONTRIBUTORS.rst
odoo/addons/sale_partner_selectable_option/readme/DESCRIPTION.rst
odoo/addons/sale_partner_selectable_option/readme/USAGE.rst
odoo/addons/sale_partner_selectable_option/static/description/icon.png
odoo/addons/sale_partner_selectable_option/static/description/index.html
odoo/addons/sale_partner_selectable_option/tests/__init__.py
odoo/addons/sale_partner_selectable_option/tests/test_sale_partner_selectable_option.py
odoo/addons/sale_partner_selectable_option/views/res_partner_view.xml
odoo13_addon_sale_partner_selectable_option-13.0.2.4.0.dist-info/METADATA
odoo13_addon_sale_partner_selectable_option-13.0.2.4.0.dist-info/WHEEL
odoo13_addon_sale_partner_selectable_option-13.0.2.4.0.dist-info/top_level.txt
odoo13_addon_sale_partner_selectable_option-13.0.2.4.0.dist-info/RECORD
